{
  "verses": [
    {
      "verse": 1,
      "quran_arabic": "بِسْمِ ٱللَّهِ ٱلرَّحْمَٰنِ ٱلرَّحِيمِ إِذَا جَآءَ نَصْرُ ٱللَّهِ وَٱلْفَتْحُ",
      "text": "When the help of God comes, and the victory,",
      "canonical_variants": [],
      "competing_variants": []
    },
    {
      "verse": 2,
      "quran_arabic": "وَرَأَيْتَ ٱلنَّاسَ يَدْخُلُونَ فِى دِينِ ٱللَّهِ أَفْوَاجًۭا",
      "text": "and you see the people entering into the religion of God in crowds,",
      "canonical_variants": [],
      "competing_variants": []
    },
    {
      "verse": 3,
      "quran_arabic": "فَسَبِّحْ بِحَمْدِ رَبِّكَ وَٱسْتَغْفِرْهُ ۚ إِنَّهُۥ كَانَ تَوَّابًۢا",
      "text": "glorify your Lord with praise, and ask forgiveness from Him. Surely He turns (in forgiveness).",
      "canonical_variants": [],
      "competing_variants": []
    }
  ]
}